exam_analyzer/__init__.py
exam_analyzer/main.py
exam_analyzer-0.0.6.dist-info/METADATA
exam_analyzer-0.0.6.dist-info/WHEEL
exam_analyzer-0.0.6.dist-info/licenses/LICENSE
exam_analyzer-0.0.6.dist-info/RECORD
