Metadata-Version: 2.1
Name: exam_analyzer
Version: 0.0.6
Summary: Analysis and Summary Tool for College Entrance Exam Grade Report
Project-URL: Homepage, https://github.com/fearlessxjdx/ExamAnalyzer
Project-URL: Bug Tracker, https://github.com/fearlessxjdx/ExamAnalyzer/issues
Author-email: xjdx <fearlessxjdx@qq.com>
License:                     GNU GENERAL PUBLIC LICENSE
License-File: LICENSE
Classifier: License :: OSI Approved :: GNU General Public License v3 or later (GPLv3+)
Classifier: Programming Language :: Python :: 3 :: Only
Classifier: Programming Language :: Python :: 3.7
Classifier: Programming Language :: Python :: 3.8
Classifier: Programming Language :: Python :: 3.9
Classifier: Programming Language :: Python :: 3.10
Classifier: Programming Language :: Python :: 3.11
Requires-Python: >=3.7
Requires-Dist: openpyxl
Requires-Dist: pandas
Requires-Dist: pypdf2
